par_term_emu_tui_rust/__init__.py
par_term_emu_tui_rust/__main__.py
par_term_emu_tui_rust/app.py
par_term_emu_tui_rust/config.py
par_term_emu_tui_rust/installer.py
par_term_emu_tui_rust/messages.py
par_term_emu_tui_rust/themes.py
par_term_emu_tui_rust/utils.py
par_term_emu_tui_rust/dialogs/__init__.py
par_term_emu_tui_rust/dialogs/config_edit_dialog.py
par_term_emu_tui_rust/install_scripts/font/install_font.sh
par_term_emu_tui_rust/install_scripts/shell_integration/install.sh
par_term_emu_tui_rust/install_scripts/shell_integration/par_term_emu_core_rust_shell_integration.bash
par_term_emu_tui_rust/install_scripts/shell_integration/par_term_emu_core_rust_shell_integration.fish
par_term_emu_tui_rust/install_scripts/shell_integration/par_term_emu_core_rust_shell_integration.zsh
par_term_emu_tui_rust/install_scripts/shell_integration/test_directory_tracking.sh
par_term_emu_tui_rust/install_scripts/terminfo/install.sh
par_term_emu_tui_rust/install_scripts/terminfo/par-term.ti
par_term_emu_tui_rust/terminal_widget/__init__.py
par_term_emu_tui_rust/terminal_widget/clipboard.py
par_term_emu_tui_rust/terminal_widget/rendering.py
par_term_emu_tui_rust/terminal_widget/screenshot.py
par_term_emu_tui_rust/terminal_widget/selection.py
par_term_emu_tui_rust/terminal_widget/terminal_widget.py
par_term_emu_tui_rust/terminal_widget/theme_manager.py
par_term_emu_tui_rust/widgets/__init__.py
par_term_emu_tui_rust/widgets/flash_line.py
par_term_emu_tui_rust/widgets/status_bar.py
par_term_emu_tui_rust/widgets/terminal_header.py
par_term_emu_tui_rust-0.2.0.dist-info/METADATA
par_term_emu_tui_rust-0.2.0.dist-info/WHEEL
par_term_emu_tui_rust-0.2.0.dist-info/entry_points.txt
par_term_emu_tui_rust-0.2.0.dist-info/licenses/LICENSE
par_term_emu_tui_rust-0.2.0.dist-info/RECORD
