Metadata-Version: 2.4
Name: par-term-emu-tui-rust
Version: 0.2.0
Summary: Textual-based TUI demonstration of par-term-emu-tui-rust terminal emulator
Project-URL: Homepage, https://github.com/paulrobello/par-term-emu-tui-rust
Project-URL: Documentation, https://github.com/paulrobello/par-term-emu-tui-rust/blob/main/README.md
Project-URL: Repository, https://github.com/paulrobello/par-term-emu-tui-rust
Project-URL: Issues, https://github.com/paulrobello/par-term-emu-tui-rust/issues
Project-URL: Discussions, https://github.com/paulrobello/par-term-emu-tui-rust/discussions
Author-email: Paul Robello <probello@gmail.com>
Maintainer-email: Paul Robello <probello@gmail.com>
License: MIT License
License-File: LICENSE
Keywords: ansi,emulator,pty,sixel,terminal,terminal-emulator,textual,true-color,tui,unicode,vt100,vt220,vt320,vt420
Classifier: Development Status :: 3 - Alpha
Classifier: Environment :: Console
Classifier: Intended Audience :: Developers
Classifier: License :: OSI Approved :: MIT License
Classifier: Operating System :: MacOS
Classifier: Operating System :: Microsoft :: Windows :: Windows 10
Classifier: Operating System :: Microsoft :: Windows :: Windows 11
Classifier: Operating System :: POSIX :: Linux
Classifier: Programming Language :: Python :: 3
Classifier: Programming Language :: Python :: 3.12
Classifier: Programming Language :: Python :: 3.13
Classifier: Programming Language :: Python :: 3.14
Classifier: Topic :: Software Development :: Libraries :: Python Modules
Classifier: Topic :: Terminals
Classifier: Topic :: Terminals :: Terminal Emulators/X Terminals
Classifier: Typing :: Typed
Requires-Python: >=3.14
Requires-Dist: par-term-emu-core-rust>=0.2.3
Requires-Dist: pyperclip>=1.11.0
Requires-Dist: pyyaml>=6.0.3
Requires-Dist: textual[syntax]>=6.6.0
Requires-Dist: xdg-base-dirs>=6.0.2
